tqdmio/__init__.py
tqdmio/_tqdmio.py
tqdmio/auto.py
tqdmio/autonotebook.py
tqdmio/utils.py
tqdmio-0.1.0.dist-info/METADATA
tqdmio-0.1.0.dist-info/WHEEL
tqdmio-0.1.0.dist-info/licenses/LICENSE
tqdmio-0.1.0.dist-info/RECORD
