Metadata-Version: 2.4
Name: tqdmio
Version: 0.1.0
Summary: A tiny IO wrapper for tqdm.
Project-URL: Homepage, https://github.com/manu-schaaf/tqdmio
Project-URL: Issues, https://github.com/manu-schaaf/tqdmio/issues
Author-email: Manuel Schaaf <manuel.schaaf@em.uni-frankfurt.de>
License-Expression: MIT
License-File: LICENSE
Classifier: Development Status :: 4 - Beta
Classifier: License :: OSI Approved :: MIT License
Classifier: Programming Language :: Python :: 3
Classifier: Programming Language :: Python :: 3.10
Classifier: Programming Language :: Python :: 3.11
Classifier: Programming Language :: Python :: 3.12
Classifier: Topic :: Software Development :: Libraries
Classifier: Topic :: Software Development :: Libraries :: Python Modules
Classifier: Topic :: Software Development :: Pre-processors
Classifier: Topic :: Software Development :: User Interfaces
Requires-Python: >=3.10
Requires-Dist: tqdm>=4.67.1
